UnicodeTokenizer.py
UnicodeTokenizer-0.2.2.dist-info/METADATA
UnicodeTokenizer-0.2.2.dist-info/WHEEL
UnicodeTokenizer-0.2.2.dist-info/top_level.txt
UnicodeTokenizer-0.2.2.dist-info/RECORD
