Metadata-Version: 2.1
Name: UnicodeTokenizer
Version: 0.2.2
Summary: UnicodeTokenizer: tokenize all Unicode text
Home-page: https://github.com/laohur/UnicodeTokenizer
Author: laohur
Author-email: laohur@gmail.com
License: [Anti-996 License](https: // github.com/996icu/996.ICU/blob/master/LICENSE)
Keywords: UnicodeTokenizer,Tokenizer,Unicode,ZiTokenizer,ZiCutter,laohur
Requires-Python: >=3.0
Requires-Dist: PyICU
Requires-Dist: tokenizers
